{
   "data" : [
      {
         "radarID" : 13093,
         "tracks" : [
            {
               "detectedID" : 1006,
               "detectedTime" : 2058.6999999999998,
               "entityID" : 13093,
               "height" : 3171.6687510000002,
               "lla" : [ 118.54831969999999, -25.70007687, -279613.22940000001 ],
               "radarID" : 13093,
               "targetType" : 3,
               "trueID" : 811,
               "velocity" : [ 273.50430779999999, 97.259958819999994, 75.735685219999993 ]
            }
         ]
      }
   ],
   "terminator" : 0
}
