{
   "data" : [
      {
         "radarID" : 12995,
         "tracks" : [
            {
               "detectedID" : 1003,
               "detectedTime" : 2328.9499999999998,
               "entityID" : 12995,
               "height" : 2300.6114680000001,
               "lla" : [ 120.7027614, -27.209862279999999, -217696.6244 ],
               "radarID" : 12995,
               "targetType" : 3,
               "trueID" : 781,
               "velocity" : [ -219.70615050000001, -185.94768640000001, 84.573431679999999 ]
            }
         ]
      }
   ],
   "terminator" : 0
}
