{
   "data" : [
      {
         "radarID" : 12889,
         "tracks" : [
            {
               "detectedID" : 1001,
               "detectedTime" : 2373.8000000000002,
               "entityID" : 12889,
               "height" : 336.64865509999998,
               "lla" : [ 117.92708090000001, -25.252982889999998, -360567.5527 ],
               "radarID" : 12889,
               "targetType" : 3,
               "trueID" : 817,
               "velocity" : [ 102.73442780000001, -121.6133186, 254.27512279999999 ]
            }
         ]
      }
   ],
   "terminator" : 0
}
