{
   "data" : [
      {
         "radarID" : 13058,
         "tracks" : [
            {
               "detectedID" : 1002,
               "detectedTime" : 642.89999999999998,
               "entityID" : 13058,
               "height" : 5004.8637849999996,
               "lla" : [ 122.38840829999999, -28.336257849999999, 8671.8209069999994 ],
               "radarID" : 13058,
               "targetType" : 3,
               "trueID" : 793,
               "velocity" : [ 250.2563227, 60.71291463, 153.90164050000001 ]
            }
         ]
      },
      {
         "radarID" : 13079,
         "tracks" : [
            {
               "detectedID" : 1004,
               "detectedTime" : 642.89999999999998,
               "entityID" : 13079,
               "height" : 5001.6959539999998,
               "lla" : [ 122.2472203, -28.243471719999999, -5373.5076920000001 ],
               "radarID" : 13079,
               "targetType" : 3,
               "trueID" : 799,
               "velocity" : [ 258.64583010000001, 150.74819629999999, 19.424620340000001 ]
            }
         ]
      }
   ],
   "terminator" : 0
}
