{
   "data" : [
      {
         "radarID" : 13009,
         "tracks" : [
            {
               "detectedID" : 1005,
               "detectedTime" : 683.54999999999995,
               "entityID" : 13009,
               "height" : 940.16894309999998,
               "lla" : [ 122.3245941, -28.295831249999999, -55515.553180000003 ],
               "radarID" : 13009,
               "targetType" : 3,
               "trueID" : 805,
               "velocity" : [ 264.28354000000002, 131.8037296, 52.744548129999998 ]
            }
         ]
      },
      {
         "radarID" : 13016,
         "tracks" : [
            {
               "detectedID" : 1005,
               "detectedTime" : 683.54999999999995,
               "entityID" : 13016,
               "height" : 902.2725117,
               "lla" : [ 122.3246181, -28.295847980000001, -55550.489589999997 ],
               "radarID" : 13016,
               "targetType" : 3,
               "trueID" : 805,
               "velocity" : [ 264.28354000000002, 131.8037296, 52.744548129999998 ]
            }
         ]
      },
      {
         "radarID" : 13065,
         "tracks" : [
            {
               "detectedID" : 1003,
               "detectedTime" : 683.54999999999995,
               "entityID" : 13065,
               "height" : 972.51232200000004,
               "lla" : [ 121.68647230000001, -27.871282180000001, -36258.05287 ],
               "radarID" : 13065,
               "targetType" : 3,
               "trueID" : 781,
               "velocity" : [ 245.00425809999999, 44.521170779999999, 167.30444969999999 ]
            }
         ]
      },
      {
         "radarID" : 13072,
         "tracks" : [
            {
               "detectedID" : 1002,
               "detectedTime" : 683.54999999999995,
               "entityID" : 13072,
               "height" : 5007.3385340000004,
               "lla" : [ 122.28742459999999, -28.269867600000001, 885.05004029999998 ],
               "radarID" : 13072,
               "targetType" : 3,
               "trueID" : 793,
               "velocity" : [ 250.5265081, 60.286091810000002, 153.62960609999999 ]
            }
         ]
      }
   ],
   "terminator" : 0
}
