{
   "data" : [
      {
         "radarID" : 13072,
         "tracks" : [
            {
               "detectedID" : 1005,
               "detectedTime" : 722.39999999999998,
               "entityID" : 13072,
               "height" : 5539.3809259999998,
               "lla" : [ 122.205871, -28.217448269999998, -56950.234750000003 ],
               "radarID" : 13072,
               "targetType" : 3,
               "trueID" : 805,
               "velocity" : [ 264.53794579999999, 131.39951859999999, 52.477059199999999 ]
            }
         ]
      }
   ],
   "terminator" : 0
}
