{
   "data" : [
      {
         "radarID" : 12995,
         "tracks" : [
            {
               "detectedID" : 1005,
               "detectedTime" : 884.29999999999995,
               "entityID" : 12995,
               "height" : 5490.3050130000001,
               "lla" : [ 121.7164269, -27.892478069999999, -81345.661410000001 ],
               "radarID" : 12995,
               "targetType" : 3,
               "trueID" : 805,
               "velocity" : [ 265.58863810000003, 129.71036169999999, 51.360465300000001 ]
            }
         ]
      },
      {
         "radarID" : 13002,
         "tracks" : [
            {
               "detectedID" : 1005,
               "detectedTime" : 884.29999999999995,
               "entityID" : 13002,
               "height" : 640.10221130000002,
               "lla" : [ 121.7172515, -27.893149050000002, -85990.500400000004 ],
               "radarID" : 13002,
               "targetType" : 3,
               "trueID" : 805,
               "velocity" : [ 265.58863810000003, 129.71036169999999, 51.360465300000001 ]
            }
         ]
      },
      {
         "radarID" : 13009,
         "tracks" : [
            {
               "detectedID" : 1005,
               "detectedTime" : 884.29999999999995,
               "entityID" : 13009,
               "height" : 310.2624343,
               "lla" : [ 121.71755090000001, -27.893356529999998, -86270.026689999999 ],
               "radarID" : 13009,
               "targetType" : 3,
               "trueID" : 805,
               "velocity" : [ 265.58863810000003, 129.71036169999999, 51.360465300000001 ]
            }
         ]
      }
   ],
   "terminator" : 0
}
