{
   "data" : [
      {
         "radarID" : 13023,
         "tracks" : [
            {
               "detectedID" : 1006,
               "detectedTime" : 970.70000000000005,
               "entityID" : 13023,
               "height" : 5772.0152420000004,
               "lla" : [ 121.7694324, -27.928387659999999, -99551.967980000001 ],
               "radarID" : 13023,
               "targetType" : 3,
               "trueID" : 811,
               "velocity" : [ 266.86180789999997, 108.73302, 83.438036060000002 ]
            }
         ]
      }
   ],
   "terminator" : 0
}
