{
   "data" : [
      {
         "radarID" : 12974,
         "tracks" : [
            {
               "detectedID" : 1002,
               "detectedTime" : 995.54999999999995,
               "entityID" : 12974,
               "height" : 5008.8865930000002,
               "lla" : [ 121.508037, -27.752149960000001, -58877.107389999997 ],
               "radarID" : 12974,
               "targetType" : 3,
               "trueID" : 793,
               "velocity" : [ 252.56963970000001, 57.003095299999998, 151.52301550000001 ]
            }
         ]
      },
      {
         "radarID" : 12981,
         "tracks" : [
            {
               "detectedID" : 1004,
               "detectedTime" : 995.54999999999995,
               "entityID" : 12981,
               "height" : 1991.4884280000001,
               "lla" : [ 121.1701877, -27.524029989999999, -54249.795169999998 ],
               "radarID" : 12981,
               "targetType" : 3,
               "trueID" : 799,
               "velocity" : [ 260.94199880000002, 147.0316799, 17.05750252 ]
            }
         ]
      }
   ],
   "terminator" : 0
}
