{
   "data" : [
      {
         "radarID" : 13086,
         "tracks" : [
            {
               "detectedID" : 1002,
               "detectedTime" : 1050.45,
               "entityID" : 13086,
               "height" : 5003.4574730000004,
               "lla" : [ 121.3701554, -27.659578629999999, -69384.624039999995 ],
               "radarID" : 13086,
               "targetType" : 3,
               "trueID" : 793,
               "velocity" : [ 252.92352819999999, 56.42416171, 151.14894269999999 ]
            }
         ]
      },
      {
         "radarID" : 13135,
         "tracks" : [
            {
               "detectedID" : 1005,
               "detectedTime" : 1050.45,
               "entityID" : 13135,
               "height" : 2781.7263659999999,
               "lla" : [ 121.2135504, -27.55478239, -108823.80160000001 ],
               "radarID" : 13135,
               "targetType" : 3,
               "trueID" : 805,
               "velocity" : [ 266.65094060000001, 127.9690827, 50.211450139999997 ]
            }
         ]
      }
   ],
   "terminator" : 0
}
