{
   "data" : [
      {
         "radarID" : 13051,
         "tracks" : [
            {
               "detectedID" : 1002,
               "detectedTime" : 1149.2,
               "entityID" : 13051,
               "height" : 358.1446613,
               "lla" : [ 121.120569, -27.491377329999999, -92986.217839999998 ],
               "radarID" : 13051,
               "targetType" : 3,
               "trueID" : 793,
               "velocity" : [ 253.55582340000001, 55.381902959999998, 150.47354999999999 ]
            }
         ]
      },
      {
         "radarID" : 13058,
         "tracks" : [
            {
               "detectedID" : 1002,
               "detectedTime" : 1149.2,
               "entityID" : 13058,
               "height" : 5003.6497879999997,
               "lla" : [ 121.1215641, -27.491932160000001, -88275.637090000004 ],
               "radarID" : 13058,
               "targetType" : 3,
               "trueID" : 793,
               "velocity" : [ 253.55582340000001, 55.381902959999998, 150.47354999999999 ]
            }
         ]
      }
   ],
   "terminator" : 0
}
