{
   "data" : [
      {
         "radarID" : 13058,
         "tracks" : [
            {
               "detectedID" : 1004,
               "detectedTime" : 293.44999999999999,
               "entityID" : 13058,
               "height" : 4907.5142130000004,
               "lla" : [ 122.66919470000001, -28.51947753, 52288.939149999998 ],
               "radarID" : 13058,
               "targetType" : 3,
               "trueID" : 799,
               "velocity" : [ 115.6823462, -88.954280729999994, 262.11587270000001 ]
            }
         ]
      }
   ],
   "terminator" : 0
}
