{
   "data" : [
      {
         "radarID" : 13135,
         "tracks" : [
            {
               "detectedID" : 1002,
               "detectedTime" : 1230.25,
               "entityID" : 13135,
               "height" : 1917.2209809999999,
               "lla" : [ 120.9171443, -27.353433420000002, -106852.72530000001 ],
               "radarID" : 13135,
               "targetType" : 3,
               "trueID" : 793,
               "velocity" : [ 254.0706935, 54.525591919999997, 149.91678529999999 ]
            }
         ]
      }
   ],
   "terminator" : 0
}
