{
   "data" : [
      {
         "radarID" : 13072,
         "tracks" : [
            {
               "detectedID" : 1004,
               "detectedTime" : 1346.45,
               "entityID" : 13072,
               "height" : 5001.1960090000002,
               "lla" : [ 120.098018, -26.7897803, -95969.964189999999 ],
               "radarID" : 13072,
               "targetType" : 3,
               "trueID" : 799,
               "velocity" : [ 263.15579330000003, 143.2934607, 14.697365359999999 ]
            }
         ]
      }
   ],
   "terminator" : 0
}
