{
   "data" : [
      {
         "radarID" : 13093,
         "tracks" : [
            {
               "detectedID" : 1002,
               "detectedTime" : 1382.0999999999999,
               "entityID" : 13093,
               "height" : 184.7568019,
               "lla" : [ 120.5351059, -27.092749210000001, -137416.5105 ],
               "radarID" : 13093,
               "targetType" : 3,
               "trueID" : 793,
               "velocity" : [ 255.02536370000001, 52.919202589999998, 148.86779989999999 ]
            }
         ]
      },
      {
         "radarID" : 13107,
         "tracks" : [
            {
               "detectedID" : 1002,
               "detectedTime" : 1382.0999999999999,
               "entityID" : 13107,
               "height" : 5010.0674840000001,
               "lla" : [ 120.5323477, -27.09073429, -132770.9988 ],
               "radarID" : 13107,
               "targetType" : 3,
               "trueID" : 793,
               "velocity" : [ 255.02536370000001, 52.919202589999998, 148.86779989999999 ]
            }
         ]
      }
   ],
   "terminator" : 0
}
