{
   "data" : [
      {
         "radarID" : 13142,
         "tracks" : [
            {
               "detectedID" : 1005,
               "detectedTime" : 1449.45,
               "entityID" : 13142,
               "height" : 5277.8748089999999,
               "lla" : [ 120.0015054, -26.724461760000001, -164900.97339999999 ],
               "radarID" : 13142,
               "targetType" : 3,
               "trueID" : 805,
               "velocity" : [ 269.1355514, 123.75592779999999, 47.439701579999998 ]
            }
         ]
      }
   ],
   "terminator" : 0
}
