{
   "data" : [
      {
         "radarID" : 13002,
         "tracks" : [
            {
               "detectedID" : 1001,
               "detectedTime" : 1547.6500000000001,
               "entityID" : 13002,
               "height" : 2090.703872,
               "lla" : [ 119.65640670000001, -26.484864630000001, -219332.62770000001 ],
               "radarID" : 13002,
               "targetType" : 3,
               "trueID" : 817,
               "velocity" : [ 271.04945600000002, 97.289178849999999, 84.065498719999994 ]
            }
         ]
      }
   ],
   "terminator" : 0
}
