{
   "data" : [
      {
         "radarID" : 13093,
         "tracks" : [
            {
               "detectedID" : 1002,
               "detectedTime" : 1550.2,
               "entityID" : 13093,
               "height" : 132.50946920000001,
               "lla" : [ 120.104917, -26.796442119999998, -169737.5675 ],
               "radarID" : 13093,
               "targetType" : 3,
               "trueID" : 793,
               "velocity" : [ 256.0670083, 51.137852870000003, 147.69768880000001 ]
            }
         ]
      }
   ],
   "terminator" : 0
}
