{
   "data" : [
      {
         "radarID" : 13023,
         "tracks" : [
            {
               "detectedID" : 1002,
               "detectedTime" : 1619.4000000000001,
               "entityID" : 13023,
               "height" : 5010.7407119999998,
               "lla" : [ 119.9277003, -26.673412939999999, -178034.8671 ],
               "radarID" : 13023,
               "targetType" : 3,
               "trueID" : 793,
               "velocity" : [ 256.49116129999999, 50.403632440000003, 147.21330789999999 ]
            }
         ]
      }
   ],
   "terminator" : 0
}
