{
   "data" : [
      {
         "radarID" : 13093,
         "tracks" : [
            {
               "detectedID" : 1001,
               "detectedTime" : 1938.7,
               "entityID" : 13093,
               "height" : 3307.3871669999999,
               "lla" : [ 118.5013517, -25.66638682, -281997.93349999998 ],
               "radarID" : 13093,
               "targetType" : 3,
               "trueID" : 817,
               "velocity" : [ 273.35176159999997, 93.132299059999994, 81.272315550000002 ]
            }
         ]
      },
      {
         "radarID" : 13107,
         "tracks" : [
            {
               "detectedID" : 1001,
               "detectedTime" : 1938.7,
               "entityID" : 13107,
               "height" : 4620.6893970000001,
               "lla" : [ 118.5018237, -25.666692579999999, -280700.74699999997 ],
               "radarID" : 13107,
               "targetType" : 3,
               "trueID" : 817,
               "velocity" : [ 273.35176159999997, 93.132299059999994, 81.272315550000002 ]
            }
         ]
      }
   ],
   "terminator" : 0
}
