{
   "data" : [
      {
         "radarID" : 13114,
         "tracks" : [
            {
               "detectedID" : 1004,
               "detectedTime" : 1940.05,
               "entityID" : 13114,
               "height" : 159.1723298,
               "lla" : [ 119.99010010000001, -26.71670744, -171957.47399999999 ],
               "radarID" : 13114,
               "targetType" : 3,
               "trueID" : 799,
               "velocity" : [ -12.840771910000001, -169.76320519999999, 247.01329670000001 ]
            }
         ]
      }
   ],
   "terminator" : 0
}
