{
   "data" : [
      {
         "radarID" : 13065,
         "tracks" : [
            {
               "detectedID" : 1004,
               "detectedTime" : 2118.9499999999998,
               "entityID" : 13065,
               "height" : 5004.2140499999996,
               "lla" : [ 120.1680441, -26.840714559999999, -188707.04319999999 ],
               "radarID" : 13065,
               "targetType" : 3,
               "trueID" : 799,
               "velocity" : [ -11.740453370000001, -171.6628475, 245.75196550000001 ]
            }
         ]
      },
      {
         "radarID" : 13107,
         "tracks" : [
            {
               "detectedID" : 1002,
               "detectedTime" : 2118.9499999999998,
               "entityID" : 13107,
               "height" : 4988.2423749999998,
               "lla" : [ 118.8376524, -25.906986790000001, -269833.86849999998 ],
               "radarID" : 13107,
               "targetType" : 3,
               "trueID" : 793,
               "velocity" : [ 11.0491715, -163.61751870000001, 251.21151119999999 ]
            }
         ]
      }
   ],
   "terminator" : 0
}
