{
   "data" : [
      {
         "radarID" : 12889,
         "tracks" : [
            {
               "detectedID" : 1005,
               "detectedTime" : 2374.5500000000002,
               "entityID" : 12889,
               "height" : 2293.843433,
               "lla" : [ 117.9308908, -25.253999239999999, -292852.84960000002 ],
               "radarID" : 12889,
               "targetType" : 3,
               "trueID" : 805,
               "velocity" : [ -41.814009059999997, -179.45855159999999, 236.7408222 ]
            }
         ]
      }
   ],
   "terminator" : 0
}
