{
   "data" : [
      {
         "radarID" : 13016,
         "tracks" : [
            {
               "detectedID" : 1003,
               "detectedTime" : 2469.5500000000002,
               "entityID" : 13016,
               "height" : 1327.1134790000001,
               "lla" : [ 121.1202433, -27.49421907, -210764.13219999999 ],
               "radarID" : 13016,
               "targetType" : 3,
               "trueID" : 781,
               "velocity" : [ -218.8438381, -187.41718180000001, 83.559407140000005 ]
            }
         ]
      }
   ],
   "terminator" : 0
}
