{
   "data" : [
      {
         "radarID" : 12924,
         "tracks" : [
            {
               "detectedID" : 1004,
               "detectedTime" : 2495.6999999999998,
               "entityID" : 12924,
               "height" : 725.28041929999995,
               "lla" : [ 120.5475654, -27.1039718, -239475.10089999999 ],
               "radarID" : 12924,
               "targetType" : 3,
               "trueID" : 799,
               "velocity" : [ -9.4209712969999995, -175.6229147, 243.03875640000001 ]
            }
         ]
      }
   ],
   "terminator" : 0
}
