{
   "data" : [
      {
         "radarID" : 12889,
         "tracks" : [
            {
               "detectedID" : 1001,
               "detectedTime" : 2631.4000000000001,
               "entityID" : 12889,
               "height" : 156.09525729999999,
               "lla" : [ 117.83577579999999, -25.187731450000001, -408835.14769999997 ],
               "radarID" : 12889,
               "targetType" : 3,
               "trueID" : 817,
               "velocity" : [ 104.18340120000001, -124.3524041, 252.35351890000001 ]
            }
         ]
      }
   ],
   "terminator" : 0
}
