{
   "data" : [
      {
         "radarID" : 12974,
         "tracks" : [
            {
               "detectedID" : 1001,
               "detectedTime" : 554.39999999999998,
               "entityID" : 12974,
               "height" : 5740.6099130000002,
               "lla" : [ 122.5565608, -28.448248840000002, -48766.621059999998 ],
               "radarID" : 12974,
               "targetType" : 3,
               "trueID" : 817,
               "velocity" : [ 264.79234029999998, 107.6971305, 91.029361159999993 ]
            }
         ]
      }
   ],
   "terminator" : 0
}
