{
   "data" : [
      {
         "radarID" : 13072,
         "tracks" : [
            {
               "detectedID" : 1004,
               "detectedTime" : 803.95000000000005,
               "entityID" : 13072,
               "height" : 5001.9186799999998,
               "lla" : [ 121.7556682, -27.917322859999999, -26476.886640000001 ],
               "radarID" : 13072,
               "targetType" : 3,
               "trueID" : 799,
               "velocity" : [ 259.70329529999998, 149.0559892, 18.34422275 ]
            }
         ]
      }
   ],
   "terminator" : 0
}
