{
   "data" : [
      {
         "radarID" : 12995,
         "tracks" : [
            {
               "detectedID" : 1001,
               "detectedTime" : 894.25,
               "entityID" : 12995,
               "height" : 5574.0319829999999,
               "lla" : [ 121.5705415, -27.795365100000001, -106765.1191 ],
               "radarID" : 12995,
               "targetType" : 3,
               "trueID" : 817,
               "velocity" : [ 266.99889460000003, 104.1610594, 88.668280490000001 ]
            }
         ]
      },
      {
         "radarID" : 13002,
         "tracks" : [
            {
               "detectedID" : 1001,
               "detectedTime" : 894.25,
               "entityID" : 13002,
               "height" : 212.08563380000001,
               "lla" : [ 121.571973, -27.796456289999998, -111807.0212 ],
               "radarID" : 13002,
               "targetType" : 3,
               "trueID" : 817,
               "velocity" : [ 266.99889460000003, 104.1610594, 88.668280490000001 ]
            }
         ]
      },
      {
         "radarID" : 13016,
         "tracks" : [
            {
               "detectedID" : 1001,
               "detectedTime" : 894.25,
               "entityID" : 13016,
               "height" : 41.55211491,
               "lla" : [ 121.5737164, -27.797624339999999, -111719.5817 ],
               "radarID" : 13016,
               "targetType" : 3,
               "trueID" : 817,
               "velocity" : [ 266.99889460000003, 104.1610594, 88.668280490000001 ]
            }
         ]
      }
   ],
   "terminator" : 0
}
