{
   "data" : [
      {
         "radarID" : 13072,
         "tracks" : [
            {
               "detectedID" : 1005,
               "detectedTime" : 941.85000000000002,
               "entityID" : 13072,
               "height" : 5458.7653499999997,
               "lla" : [ 121.5422404, -27.77592847, -89981.86752 ],
               "radarID" : 13072,
               "targetType" : 3,
               "trueID" : 805,
               "velocity" : [ 265.95842640000001, 129.10811530000001, 50.962829720000002 ]
            }
         ]
      }
   ],
   "terminator" : 0
}
