{
   "data" : [
      {
         "radarID" : 13079,
         "tracks" : [
            {
               "detectedID" : 1002,
               "detectedTime" : 1011.1,
               "entityID" : 13079,
               "height" : 5003.4499770000002,
               "lla" : [ 121.46900890000001, -27.725977149999999, -61853.78067 ],
               "radarID" : 13079,
               "targetType" : 3,
               "trueID" : 793,
               "velocity" : [ 252.6700472, 56.839154120000003, 151.41716489999999 ]
            }
         ]
      }
   ],
   "terminator" : 0
}
