{
   "data" : [
      {
         "radarID" : 13023,
         "tracks" : [
            {
               "detectedID" : 1004,
               "detectedTime" : 1070.4000000000001,
               "entityID" : 13023,
               "height" : 5001.2247889999999,
               "lla" : [ 120.9418544, -27.36910181, -60920.679329999999 ],
               "radarID" : 13023,
               "targetType" : 3,
               "trueID" : 799,
               "velocity" : [ 261.4201764, 146.2376204, 16.554447509999999 ]
            }
         ]
      },
      {
         "radarID" : 13135,
         "tracks" : [
            {
               "detectedID" : 1005,
               "detectedTime" : 1070.4000000000001,
               "entityID" : 13135,
               "height" : 2765.0477999999998,
               "lla" : [ 121.15295999999999, -27.513820689999999, -111798.164 ],
               "radarID" : 13135,
               "targetType" : 3,
               "trueID" : 805,
               "velocity" : [ 266.7774028, 127.75947840000001, 50.07327677 ]
            }
         ]
      }
   ],
   "terminator" : 0
}
