{
   "data" : [
      {
         "radarID" : 13065,
         "tracks" : [
            {
               "detectedID" : 1001,
               "detectedTime" : 262.10000000000002,
               "entityID" : 13065,
               "height" : 5880.976095,
               "lla" : [ 123.39968829999999, -28.994570790000001, 1620.2130520000001 ],
               "radarID" : 13065,
               "targetType" : 3,
               "trueID" : 817,
               "velocity" : [ 262.84046080000002, 110.7166658, 93.041453439999998 ]
            }
         ]
      },
      {
         "radarID" : 13079,
         "tracks" : [
            {
               "detectedID" : 1001,
               "detectedTime" : 262.10000000000002,
               "entityID" : 13079,
               "height" : 5882.1747409999998,
               "lla" : [ 123.3997078, -28.994583290000001, 1621.8002759999999 ],
               "radarID" : 13079,
               "targetType" : 3,
               "trueID" : 817,
               "velocity" : [ 262.84046080000002, 110.7166658, 93.041453439999998 ]
            }
         ]
      },
      {
         "radarID" : 13086,
         "tracks" : [
            {
               "detectedID" : 1001,
               "detectedTime" : 262.10000000000002,
               "entityID" : 13086,
               "height" : 5874.6599580000002,
               "lla" : [ 123.39944079999999, -28.994412140000001, 1603.372543 ],
               "radarID" : 13086,
               "targetType" : 3,
               "trueID" : 817,
               "velocity" : [ 262.84046080000002, 110.7166658, 93.041453439999998 ]
            }
         ]
      }
   ],
   "terminator" : 0
}
