{
   "data" : [
      {
         "radarID" : 13030,
         "tracks" : [
            {
               "detectedID" : 1004,
               "detectedTime" : 1138.3499999999999,
               "entityID" : 13030,
               "height" : 623.33155499999998,
               "lla" : [ 120.732738, -27.226678830000001, -74033.212029999995 ],
               "radarID" : 13030,
               "targetType" : 3,
               "trueID" : 799,
               "velocity" : [ 261.85147890000002, 145.51519099999999, 16.097584170000001 ]
            }
         ]
      }
   ],
   "terminator" : 0
}
