{
   "data" : [
      {
         "radarID" : 13002,
         "tracks" : [
            {
               "detectedID" : 1001,
               "detectedTime" : 1197.0999999999999,
               "entityID" : 13002,
               "height" : 334.10653250000001,
               "lla" : [ 120.6841526, -27.19568353, -162875.87890000001 ],
               "radarID" : 13002,
               "targetType" : 3,
               "trueID" : 817,
               "velocity" : [ 268.90785110000002, 100.98770140000001, 86.545085259999993 ]
            }
         ]
      }
   ],
   "terminator" : 0
}
