{
   "data" : [
      {
         "radarID" : 13135,
         "tracks" : [
            {
               "detectedID" : 1005,
               "detectedTime" : 1319.8,
               "entityID" : 13135,
               "height" : 3035.4150949999998,
               "lla" : [ 120.3956725, -26.997034450000001, -148273.2408 ],
               "radarID" : 13135,
               "targetType" : 3,
               "trueID" : 805,
               "velocity" : [ 268.33853340000002, 125.12977119999999, 48.342236509999999 ]
            }
         ]
      }
   ],
   "terminator" : 0
}
