{
   "data" : [
      {
         "radarID" : 13023,
         "tracks" : [
            {
               "detectedID" : 1004,
               "detectedTime" : 1398.6500000000001,
               "entityID" : 13023,
               "height" : 5002.7171539999999,
               "lla" : [ 119.9382147, -26.678822329999999, -102531.345 ],
               "radarID" : 13023,
               "targetType" : 3,
               "trueID" : 799,
               "velocity" : [ 263.47905479999997, 142.73396049999999, 14.34587805 ]
            }
         ]
      }
   ],
   "terminator" : 0
}
