{
   "data" : [
      {
         "radarID" : 12931,
         "tracks" : [
            {
               "detectedID" : 1002,
               "detectedTime" : 1416.7,
               "entityID" : 12931,
               "height" : 5003.7226190000001,
               "lla" : [ 120.4445877, -27.0305167, -139382.0699 ],
               "radarID" : 12931,
               "targetType" : 3,
               "trueID" : 793,
               "velocity" : [ 255.2410715, 52.552806910000001, 148.6277159 ]
            }
         ]
      },
      {
         "radarID" : 12938,
         "tracks" : [
            {
               "detectedID" : 1002,
               "detectedTime" : 1416.7,
               "entityID" : 12938,
               "height" : 5007.3582669999996,
               "lla" : [ 120.4443074, -27.03032365, -139383.19940000001 ],
               "radarID" : 12938,
               "targetType" : 3,
               "trueID" : 793,
               "velocity" : [ 255.2410715, 52.552806910000001, 148.6277159 ]
            }
         ]
      },
      {
         "radarID" : 12974,
         "tracks" : [
            {
               "detectedID" : 1002,
               "detectedTime" : 1416.7,
               "entityID" : 12974,
               "height" : 5009.7086440000003,
               "lla" : [ 120.44429, -27.03031163, -139382.32740000001 ],
               "radarID" : 12974,
               "targetType" : 3,
               "trueID" : 793,
               "velocity" : [ 255.2410715, 52.552806910000001, 148.6277159 ]
            }
         ]
      }
   ],
   "terminator" : 0
}
