{
   "data" : [
      {
         "radarID" : 12931,
         "tracks" : [
            {
               "detectedID" : 1006,
               "detectedTime" : 1447.3,
               "entityID" : 12931,
               "height" : 5542.8915960000004,
               "lla" : [ 120.3656453, -26.977104019999999, -178600.3321 ],
               "radarID" : 12931,
               "targetType" : 3,
               "trueID" : 811,
               "velocity" : [ 269.8584477, 103.740257, 80.089807550000003 ]
            }
         ]
      },
      {
         "radarID" : 12988,
         "tracks" : [
            {
               "detectedID" : 1005,
               "detectedTime" : 1447.3,
               "entityID" : 12988,
               "height" : 5275.9349309999998,
               "lla" : [ 120.0080087, -26.728978000000001, -164608.31890000001 ],
               "radarID" : 12988,
               "targetType" : 3,
               "trueID" : 805,
               "velocity" : [ 269.12241569999998, 123.7787479, 47.454682980000001 ]
            }
         ]
      }
   ],
   "terminator" : 0
}
