{
   "data" : [
      {
         "radarID" : 13065,
         "tracks" : [
            {
               "detectedID" : 1002,
               "detectedTime" : 1508.6500000000001,
               "entityID" : 13065,
               "height" : 5006.4620420000001,
               "lla" : [ 120.21034400000001, -26.869199179999999, -156931.3725 ],
               "radarID" : 13065,
               "targetType" : 3,
               "trueID" : 793,
               "velocity" : [ 255.8110284, 51.578450220000001, 147.98777390000001 ]
            }
         ]
      }
   ],
   "terminator" : 0
}
