{
   "data" : [
      {
         "radarID" : 12938,
         "tracks" : [
            {
               "detectedID" : 1002,
               "detectedTime" : 1526.9000000000001,
               "entityID" : 12938,
               "height" : 5004.0123080000003,
               "lla" : [ 120.1640156, -26.83719297, -160401.78279999999 ],
               "radarID" : 12938,
               "targetType" : 3,
               "trueID" : 793,
               "velocity" : [ 255.92358279999999, 51.384950240000002, 147.8604296 ]
            }
         ]
      }
   ],
   "terminator" : 0
}
