{
   "data" : [
      {
         "radarID" : 13030,
         "tracks" : [
            {
               "detectedID" : 1004,
               "detectedTime" : 1548.0,
               "entityID" : 13030,
               "height" : 3030.80881,
               "lla" : [ 119.6047258, -26.44615808, -122961.2582 ],
               "radarID" : 13030,
               "targetType" : 3,
               "trueID" : 799,
               "velocity" : [ -15.249155119999999, -165.55777499999999, 249.71601150000001 ]
            }
         ]
      },
      {
         "radarID" : 13037,
         "tracks" : [
            {
               "detectedID" : 1004,
               "detectedTime" : 1548.0,
               "entityID" : 13037,
               "height" : 3050.8541690000002,
               "lla" : [ 119.6047533, -26.446176829999999, -122938.28969999999 ],
               "radarID" : 13037,
               "targetType" : 3,
               "trueID" : 799,
               "velocity" : [ -15.249155119999999, -165.55777499999999, 249.71601150000001 ]
            }
         ]
      },
      {
         "radarID" : 13044,
         "tracks" : [
            {
               "detectedID" : 1004,
               "detectedTime" : 1548.0,
               "entityID" : 13044,
               "height" : 3016.3987550000002,
               "lla" : [ 119.6046135, -26.446079839999999, -122984.7277 ],
               "radarID" : 13044,
               "targetType" : 3,
               "trueID" : 799,
               "velocity" : [ -15.249155119999999, -165.55777499999999, 249.71601150000001 ]
            }
         ]
      }
   ],
   "terminator" : 0
}
