{
   "data" : [
      {
         "radarID" : 13030,
         "tracks" : [
            {
               "detectedID" : 1005,
               "detectedTime" : 1548.75,
               "entityID" : 13030,
               "height" : 4884.6208310000002,
               "lla" : [ 119.69902759999999, -26.513708139999999, -179684.64670000001 ],
               "radarID" : 13030,
               "targetType" : 3,
               "trueID" : 805,
               "velocity" : [ 269.7392476, 122.7005861, 46.74724002 ]
            }
         ]
      },
      {
         "radarID" : 13044,
         "tracks" : [
            {
               "detectedID" : 1005,
               "detectedTime" : 1548.75,
               "entityID" : 13044,
               "height" : 4890.5948989999997,
               "lla" : [ 119.6990303, -26.51370988, -179678.6655 ],
               "radarID" : 13044,
               "targetType" : 3,
               "trueID" : 805,
               "velocity" : [ 269.7392476, 122.7005861, 46.74724002 ]
            }
         ]
      },
      {
         "radarID" : 13058,
         "tracks" : [
            {
               "detectedID" : 1002,
               "detectedTime" : 1548.75,
               "entityID" : 13058,
               "height" : 5005.8655779999999,
               "lla" : [ 120.1081859, -26.7985781, -164567.8204 ],
               "radarID" : 13058,
               "targetType" : 3,
               "trueID" : 793,
               "velocity" : [ 256.05809160000001, 51.153231920000003, 147.70782159999999 ]
            }
         ]
      },
      {
         "radarID" : 13065,
         "tracks" : [
            {
               "detectedID" : 1001,
               "detectedTime" : 1548.75,
               "entityID" : 13065,
               "height" : 5272.0044459999999,
               "lla" : [ 119.6542542, -26.48327995, -216410.9522 ],
               "radarID" : 13065,
               "targetType" : 3,
               "trueID" : 817,
               "velocity" : [ 271.05606080000001, 97.277531269999997, 84.057681470000006 ]
            }
         ]
      },
      {
         "radarID" : 13072,
         "tracks" : [
            {
               "detectedID" : 1006,
               "detectedTime" : 1548.75,
               "entityID" : 13072,
               "height" : 5496.3533630000002,
               "lla" : [ 120.0654914, -26.76972365, -195220.7978 ],
               "radarID" : 13072,
               "targetType" : 3,
               "trueID" : 811,
               "velocity" : [ 270.47889850000001, 102.67072779999999, 79.371828440000002 ]
            }
         ]
      },
      {
         "radarID" : 13079,
         "tracks" : [
            {
               "detectedID" : 1002,
               "detectedTime" : 1548.75,
               "entityID" : 13079,
               "height" : 5006.0944369999997,
               "lla" : [ 120.10816320000001, -26.79856238, -164569.43890000001 ],
               "radarID" : 13079,
               "targetType" : 3,
               "trueID" : 793,
               "velocity" : [ 256.05809160000001, 51.153231920000003, 147.70782159999999 ]
            }
         ]
      },
      {
         "radarID" : 13086,
         "tracks" : [
            {
               "detectedID" : 1002,
               "detectedTime" : 1548.75,
               "entityID" : 13086,
               "height" : 5002.5768509999998,
               "lla" : [ 120.1082483, -26.798621319999999, -164562.9105 ],
               "radarID" : 13086,
               "targetType" : 3,
               "trueID" : 793,
               "velocity" : [ 256.05809160000001, 51.153231920000003, 147.70782159999999 ]
            }
         ]
      }
   ],
   "terminator" : 0
}
