{
   "data" : [
      {
         "radarID" : 13107,
         "tracks" : [
            {
               "detectedID" : 1006,
               "detectedTime" : 1689.45,
               "entityID" : 13107,
               "height" : 5418.4607159999996,
               "lla" : [ 119.6482987, -26.479149809999999, -218162.4958 ],
               "radarID" : 13107,
               "targetType" : 3,
               "trueID" : 811,
               "velocity" : [ 271.32922050000002, 101.1835738, 78.37307251 ]
            }
         ]
      }
   ],
   "terminator" : 0
}
