{
   "data" : [
      {
         "radarID" : 12931,
         "tracks" : [
            {
               "detectedID" : 1001,
               "detectedTime" : 13.6,
               "entityID" : 12931,
               "height" : 5998.2735350000003,
               "lla" : [ 124.1097219, -29.446139219999999, 44575.718719999997 ],
               "radarID" : 12931,
               "targetType" : 3,
               "trueID" : 817,
               "velocity" : [ 191.03796410000001, 82.850576469999993, 69.298499100000001 ]
            }
         ]
      },
      {
         "radarID" : 12938,
         "tracks" : [
            {
               "detectedID" : 1001,
               "detectedTime" : 13.6,
               "entityID" : 12938,
               "height" : 6006.7034460000004,
               "lla" : [ 124.1100764, -29.44636212, 44621.650889999997 ],
               "radarID" : 12938,
               "targetType" : 3,
               "trueID" : 817,
               "velocity" : [ 191.03796410000001, 82.850576469999993, 69.298499100000001 ]
            }
         ]
      }
   ],
   "terminator" : 0
}
