{
   "data" : [
      {
         "radarID" : 13002,
         "tracks" : [
            {
               "detectedID" : 1002,
               "detectedTime" : 1857.55,
               "entityID" : 13002,
               "height" : 2990.1555050000002,
               "lla" : [ 119.31590730000001, -26.24541542, -225275.92720000001 ],
               "radarID" : 13002,
               "targetType" : 3,
               "trueID" : 793,
               "velocity" : [ 257.93009089999998, 47.872869199999997, 145.5343829 ]
            }
         ]
      }
   ],
   "terminator" : 0
}
